{
  "users": [
    {
      "username": "khalid",
      "email": "hjhjh@44.Com",
      "password": "jkyzgzehzeyg",
      "id": 3
    },
    {
      "username": "hghg",
      "email": "hjhjh@44.Com",
      "password": "ugytyy",
      "id": 4
    },
    {
      "username": "omar",
      "email": "omar.ajbar.dev@gmail.com",
      "password": "azerty",
      "id": 5
    },
    {
      "username": "Omar",
      "email": "ajbar.omar.dev@gmail.com",
      "password": "hhjhhh",
      "id": 9
    },
    {
      "username": "salah",
      "email": "omar.ajbar.dev@gmail.com",
      "password": "122222",
      "id": 12
    },
    {
      "username": "Ajbar",
      "email": "omar.ajbar.dev@gmail.com",
      "password": "dfghjkl",
      "id": 14
    },
    {
      "username": "mosalah",
      "email": "hjhjh@44.Com",
      "password": "azereldkjcdskjjk",
      "id": 15
    },
    {
      "username": "moaad",
      "email": "inkopc67@gmail.com",
      "password": "azerty",
      "id": 16
    },
    {
      "username": "khalido",
      "email": "omarajabar@gmail.com",
      "password": "azerty",
      "id": 17
    },
    {
      "username": "ahmed",
      "email": "hjhjh@44.Com",
      "password": "azerty",
      "id": 18
    }
  ]
}